pyplate/__init__.py
pyplate/cli/__init__.py
pyplate/cli/__main__.py
pyplate_boilerplate-1.0.0.dist-info/METADATA
pyplate_boilerplate-1.0.0.dist-info/WHEEL
pyplate_boilerplate-1.0.0.dist-info/RECORD
